setup.cfg
setup.py
jmpy/__init__.py
jmpy.egg-info/PKG-INFO
jmpy.egg-info/SOURCES.txt
jmpy.egg-info/dependency_links.txt
jmpy.egg-info/requires.txt
jmpy.egg-info/top_level.txt
jmpy.egg-info/zip-safe
jmpy/bayes/__init__.py
jmpy/bayes/oneway.py
jmpy/common/__init__.py
jmpy/common/colors.py
jmpy/common/stats.py
jmpy/modeling/__init__.py
jmpy/modeling/lm.py
jmpy/plotting/__init__.py
jmpy/plotting/boxplot.py
jmpy/plotting/components.py
jmpy/plotting/contour.py
jmpy/plotting/cumprob.py
jmpy/plotting/grid.py
jmpy/plotting/histogram.py
jmpy/plotting/scatter.py
jmpy/plotting/varchart.py