Metadata-Version: 1.0
Name: jmpy
Version: 0.10.3
Summary: JMP Style Plotting and Modeling
Home-page: UNKNOWN
Author: David Daycock
Author-email: ddaycock@micron.com
License: MIT
Platform: UNKNOWN
